ytextract/__init__.py
ytextract/__main__.py
ytextract/captions.py
ytextract/cipher.py
ytextract/cli.py
ytextract/download_helper.py
ytextract/exceptions.py
ytextract/extract.py
ytextract/helpers.py
ytextract/innertube.py
ytextract/itags.py
ytextract/metadata.py
ytextract/monostate.py
ytextract/parser.py
ytextract/query.py
ytextract/request.py
ytextract/server.py
ytextract/streams.py
ytextract-0.0.2.dist-info/licenses/LICENSE
ytextract-0.0.2.dist-info/METADATA
ytextract-0.0.2.dist-info/WHEEL
ytextract-0.0.2.dist-info/entry_points.txt
ytextract-0.0.2.dist-info/top_level.txt
ytextract-0.0.2.dist-info/zip-safe
ytextract-0.0.2.dist-info/RECORD
