Metadata-Version: 2.4
Name: ytextract
Version: 0.0.2
Summary: Python 3 library for downloading YouTube Videos.
Home-page: https://github.com/Josh-XT/ytextract
Author: Josh-XT
License: The Unlicense (Unlicense)
Project-URL: Bug Reports, https://github.com/Josh-XT/ytextract/issues
Keywords: youtube,download,video,stream
Classifier: Development Status :: 5 - Production/Stable
Classifier: Environment :: Console
Classifier: Intended Audience :: Developers
Classifier: License :: OSI Approved :: The Unlicense (Unlicense)
Classifier: Natural Language :: English
Classifier: Operating System :: OS Independent
Classifier: Programming Language :: Python :: 3.7
Classifier: Programming Language :: Python :: 3.8
Classifier: Programming Language :: Python :: 3.9
Classifier: Programming Language :: Python :: 3.10
Classifier: Programming Language :: Python :: 3.11
Classifier: Programming Language :: Python
Classifier: Topic :: Internet
Classifier: Topic :: Multimedia :: Video
Classifier: Topic :: Software Development :: Libraries :: Python Modules
Classifier: Topic :: Terminals
Classifier: Topic :: Utilities
Requires-Python: >=3.7
License-File: LICENSE
Requires-Dist: selenium
Requires-Dist: webdriver-manager
Requires-Dist: fastapi
Requires-Dist: uvicorn
Requires-Dist: pydantic
Dynamic: author
Dynamic: classifier
Dynamic: description
Dynamic: description-content-type
Dynamic: home-page
Dynamic: keywords
Dynamic: license
Dynamic: license-file
Dynamic: project-url
Dynamic: requires-dist
Dynamic: requires-python
Dynamic: summary
